clarityviz/__init__.py
clarityviz/atlasregiongraph.py
clarityviz/claritybase.py
clarityviz/clarityviz.py
clarityviz/copy.py
clarityviz/densitygraph.py
clarityviz-0.0.6.dist-info/DESCRIPTION.rst
clarityviz-0.0.6.dist-info/METADATA
clarityviz-0.0.6.dist-info/RECORD
clarityviz-0.0.6.dist-info/WHEEL
clarityviz-0.0.6.dist-info/metadata.json
clarityviz-0.0.6.dist-info/top_level.txt
